next_gen_ui_rhds_renderer/__init__.py
next_gen_ui_rhds_renderer/rhds_renderer.py
next_gen_ui_rhds_renderer/templates/audio-player.jinja
next_gen_ui_rhds_renderer/templates/image.jinja
next_gen_ui_rhds_renderer/templates/one-card.jinja
next_gen_ui_rhds_renderer/templates/set-of-cards.jinja
next_gen_ui_rhds_renderer/templates/table.jinja
next_gen_ui_rhds_renderer/templates/video-player.jinja
next_gen_ui_rhds_renderer-0.3.0.dist-info/METADATA
next_gen_ui_rhds_renderer-0.3.0.dist-info/WHEEL
next_gen_ui_rhds_renderer-0.3.0.dist-info/entry_points.txt
next_gen_ui_rhds_renderer-0.3.0.dist-info/namespace_packages.txt
next_gen_ui_rhds_renderer-0.3.0.dist-info/top_level.txt
next_gen_ui_rhds_renderer-0.3.0.dist-info/RECORD
