Metadata-Version: 2.1
Name: next_gen_ui_rhds_renderer
Version: 0.3.0
Summary: RHDS Extension for Next Gen UI Agent
Home-page: https://github.com/RedHat-UX/next-gen-ui-agent
License: Apache-2.0
Classifier: Programming Language :: Python :: 3
Classifier: Programming Language :: Python :: 3.12
Classifier: Programming Language :: Python :: 3.13
Classifier: License :: OSI Approved :: Apache Software License
Requires-Python: <3.14,>=3.12
Requires-Dist: jinja2
Requires-Dist: next-gen-ui-agent==0.3.0
Requires-Dist: typing-extensions
